{
    "meta": {
        "query": "cars",
        "gl": "newyork",
        "hl": "en",
        "has_pic": false,
        "posted_today": false,
        "show_duplicates": false,
        "search_title_only": false,
        "search_distance": 0,
        "page": 0,
        "purveyor": "",
        "min_price": 0,
        "max_price": 0,
        "auto_make_model": "",
        "crypto_currency_ok": false,
        "delivery_available": false,
        "results": 302
    },
    "data": [
        {
            "title": "Campbells Soup & Mobil Gas Vintage Toy Trucks",
            "url": "https://newyork.craigslist.org/lgi/clt/d/valley-stream-campbells-soup-mobil-gas/7810812953.html",
            "price": "$10",
            "location": "Valley Stream"
        },
        {
            "title": "We buy cars",
            "url": "https://newyork.craigslist.org/que/wan/d/new-york-we-buy-cars/7815920611.html",
            "price": "0",
            "location": "New York"
        },
        {
            "title": "Idemitsu OE Power Steering Fluid (12 Packs of 12oz)  For Asian Cars",
            "url": "https://newyork.craigslist.org/brk/pts/d/brooklyn-idemitsu-oe-power-steering/7815399488.html",
            "price": "$80",
            "location": "Nostrand Ave / Ave Z"
        },
        {
            "title": "We junk cars",
            "url": "https://newyork.craigslist.org/que/wan/d/astoria-we-junk-cars/7815920858.html",
            "price": "0",
            "location": "New York"
        },
        {
            "title": "2015+NISSAN TOYOTA JUNK CARS WANTED CASH",
            "url": "https://newyork.craigslist.org/brk/ctd/d/brooklyn-2015nissan-toyota-junk-cars/7815910956.html",
            "price": "$2,500",
            "location": "Anywhere"
        },
        {
            "title": "Ca$h 4 All Vehicles  All Old Used Unwanted Junk Cars Trucks Vans Suvs",
            "url": "https://newyork.craigslist.org/brk/cto/d/brooklyn-cah-all-vehicles-all-old-used/7815891394.html",
            "price": "$5,000",
            "location": "brooklyn"
        },
        {
            "title": "Convolut of Matchbox, Hotwheels and other cars",
            "url": "https://newyork.craigslist.org/wch/tag/d/buchanan-convolut-of-matchbox-hotwheels/7815873429.html",
            "price": "$20",
            "location": "Buchanan"
        },
        {
            "title": "Large Baby Shade + suction on shades for back and side cars windows",
            "url": "https://newyork.craigslist.org/mnh/bab/d/new-york-city-large-baby-shade-suction/7808357166.html",
            "price": "$15",
            "location": "TriBeCa"
        },
        {
            "title": "Wooden City - Cars, Streets, Trains, Signs 100+ pieces",
            "url": "https://newyork.craigslist.org/wch/tag/d/buchanan-wooden-city-cars-streets/7815871264.html",
            "price": "$40",
            "location": "Buchanan"
        },
        {
            "title": "DIE CAST CARS (3)VW,VETTE,MUSTANG",
            "url": "https://newyork.craigslist.org/que/clt/d/ozone-park-die-cast-cars-3vwvettemustang/7814949305.html",
            "price": "$25",
            "location": "OZONE PARK"
        },
        {
            "title": "Large Baby Shade + suction on shades for back and side cars windows",
            "url": "https://newyork.craigslist.org/mnh/bab/d/new-york-city-large-baby-shade-suction/7808344223.html",
            "price": "$15",
            "location": "TriBeCa"
        },
        {
            "title": "Matchbox Cars & More",
            "url": "https://newyork.craigslist.org/mnh/tag/d/new-york-matchbox-cars-more/7815131778.html",
            "price": "$15",
            "location": "Upper East Side"
        },
        {
            "title": "Wheel Locks for Ford cars",
            "url": "https://newyork.craigslist.org/brx/for/d/bronx-wheel-locks-for-ford-cars/7815792002.html",
            "price": "$10",
            "location": "Bronx"
        },
        {
            "title": "Idemitsu OE Power Steering Fluid (12 Packs of 12oz)  For Asian Cars",
            "url": "https://newyork.craigslist.org/brk/pts/d/brooklyn-idemitsu-oe-power-steering/7811629772.html",
            "price": "$100",
            "location": "Nostrand Ave / Ave Z"
        },
        {
            "title": "WANTED $ $ AURORA H, O, DETROIT AFX SLOT CARS WANTED paying top dollar",
            "url": "https://newyork.craigslist.org/lgi/wan/d/linden-wanted-aurora-o-detroit-afx-slot/7810623258.html",
            "price": "0",
            "location": "linden"
        },
        {
            "title": "WANTED $$$ AURORA H, O, DETROIT AFX SLOT CARS WANTED paying top dollar",
            "url": "https://newyork.craigslist.org/lgi/wan/d/linden-wanted-aurora-o-detroit-afx-slot/7811335299.html",
            "price": "0",
            "location": "linden"
        },
        {
            "title": "WANTED $$$ AURORA H, O, DETROIT AFX SLOT CARS WANTED paying top dollar",
            "url": "https://newyork.craigslist.org/lgi/wan/d/linden-wanted-aurora-o-detroit-afx-slot/7814036574.html",
            "price": "0",
            "location": "linden"
        },
        {
            "title": "Lamborghini Diablo \"Hot Cars\" Collector Brochure",
            "url": "https://newyork.craigslist.org/brk/clt/d/brooklyn-lamborghini-diablo-hot-cars/7814502348.html",
            "price": "$5",
            "location": "Brooklyn"
        },
        {
            "title": "Hot Wheels electronic 6-lane racing track (and cars)",
            "url": "https://newyork.craigslist.org/wch/bab/d/mount-vernon-hot-wheels-electronic-lane/7814701205.html",
            "price": "$55",
            "location": "Bronxville/Mount Vernon"
        },
        {
            "title": "1988 REPRINT MOTOR CARS 1923 CIGARETTE CARDS LAMBERT & BUTLER FRAMED",
            "url": "https://newyork.craigslist.org/lgi/fuo/d/floral-park-1988-reprint-motor-cars/7811119023.html",
            "price": "$99",
            "location": "Floral Park"
        },
        {
            "title": "Accident Cars Bought Daily",
            "url": "https://newyork.craigslist.org/brk/wto/d/bronx-accident-cars-bought-daily/7815761612.html",
            "price": "$500",
            "location": "Bklyn"
        },
        {
            "title": "There are some electronic items and other items, such as cars, that I would like",
            "url": "https://newyork.craigslist.org/lgi/app/d/point-lookout-there-are-some-electronic/7815682266.html",
            "price": "$0",
            "location": "Point Lookout"
        },
        {
            "title": "James Bond cars",
            "url": "https://newyork.craigslist.org/lgi/tag/d/port-washington-james-bond-cars/7811355343.html",
            "price": "$30",
            "location": "Port Washington"
        },
        {
            "title": "Franklin mint die cast cars",
            "url": "https://newyork.craigslist.org/lgi/clt/d/port-washington-franklin-mint-die-cast/7808552933.html",
            "price": "$225",
            "location": "Port Washington"
        },
        {
            "title": "Wanted:  Classic Foreign Cars, Mercedes, Porsche, BMW, Lancia, Jaguar",
            "url": "https://newyork.craigslist.org/wch/wan/d/yorktown-heights-wanted-classic-foreign/7808694037.html",
            "price": "0",
            "location": "Yorktown"
        },
        {
            "title": "Disney Arts and Craft Activity Set by Disney Cars with 130 pieces",
            "url": "https://newyork.craigslist.org/lgi/art/d/lynbrook-disney-arts-and-craft-activity/7815557569.html",
            "price": "$20",
            "location": "nassau county"
        },
        {
            "title": "(5) North Pole Express Christmas Train Replacement Cars",
            "url": "https://newyork.craigslist.org/lgi/for/d/east-islip-north-pole-express-christmas/7815554131.html",
            "price": "$0",
            "location": "long island"
        },
        {
            "title": "SCX SCALEXTRIC 88750 ANALOG PIT BOX TRACK FOR 1/32 Scale SLOT CARS",
            "url": "https://newyork.craigslist.org/brk/ele/d/brooklyn-scx-scalextric-analog-pit-box/7808032997.html",
            "price": "$99",
            "location": "Brooklyn NY"
        },
        {
            "title": "Die Cast 1/18 Scale Cars",
            "url": "https://newyork.craigslist.org/brx/tag/d/bronx-die-cast-18-scale-cars/7815528893.html",
            "price": "$20",
            "location": "Bronx"
        },
        {
            "title": "Battery charger RC cars",
            "url": "https://newyork.craigslist.org/lgi/ele/d/east-northport-battery-charger-rc-cars/7815525041.html",
            "price": "$20",
            "location": "E. Northport"
        },
        {
            "title": "Pontiac Trans Am \"Hot Cars\" Collector Brochure",
            "url": "https://newyork.craigslist.org/brk/clt/d/brooklyn-pontiac-trans-am-hot-cars/7814017592.html",
            "price": "$5",
            "location": "Brooklyn"
        },
        {
            "title": "Corvette Sting Ray \"Hot Cars\" Collector Brochure",
            "url": "https://newyork.craigslist.org/brk/clt/d/brooklyn-corvette-sting-ray-hot-cars/7814017558.html",
            "price": "$5",
            "location": "Brooklyn"
        },
        {
            "title": "1953 Cadillac Eldorado \"Hot Cars\" Collector Brochure",
            "url": "https://newyork.craigslist.org/brk/clt/d/brooklyn-1953-cadillac-eldorado-hot/7814017529.html",
            "price": "$5",
            "location": "Brooklyn"
        },
        {
            "title": "1999 mobile 1. 25th anniversary special edition 3 cars (Have 20 available.)",
            "url": "https://newyork.craigslist.org/stn/tag/d/staten-island-1999-mobile-25th/7807807748.html",
            "price": "$10",
            "location": "Staten Island"
        },
        {
            "title": "Temporary Plate",
            "url": "https://newyork.craigslist.org/brk/pts/d/brooklyn-temporary-plate/7808621857.html",
            "price": "$0",
            "location": "brooklyn"
        },
        {
            "title": "PISTON KEY CHAIN OR EAGLE HOOD ORNAMENT FOR CARS",
            "url": "https://newyork.craigslist.org/que/pts/d/oakland-gardens-piston-key-chain-or/7808407115.html",
            "price": "$5",
            "location": "bayside/queens"
        },
        {
            "title": "WE BUY JUNK CARS  FOR CASH.718-218-9244 - $1 (Brooklyn)",
            "url": "https://newyork.craigslist.org/brk/ptd/d/brooklyn-we-buy-junk-cars-for-cash/7815482728.html",
            "price": "$0",
            "location": "BROOKLYN"
        },
        {
            "title": "HUGE LOTS OF 30 TOY TRUCKS, CARS, MOTORCYCLES, TRAILERS, BOY, PLAY",
            "url": "https://newyork.craigslist.org/fct/tag/d/wilton-huge-lots-of-30-toy-trucks-cars/7812732222.html",
            "price": "$45",
            "location": "Wilton, CT"
        },
        {
            "title": "Good Year tire inflator for motorcycle, cars, bicycle and inflatables",
            "url": "https://newyork.craigslist.org/que/wto/d/rego-park-good-year-tire-inflator-for/7815442463.html",
            "price": "$25",
            "location": "Rego Park"
        },
        {
            "title": "Parts for RC Cars",
            "url": "https://newyork.craigslist.org/fct/tag/d/wilton-parts-for-rc-cars/7815373845.html",
            "price": "$100",
            "location": "Wilton"
        },
        {
            "title": "2006 Mercedes E350 4matic wagon 100 plus cheap cars in stock",
            "url": "https://newyork.craigslist.org/brk/ctd/d/burlington-2006-mercedes-e350-4matic/7815303338.html",
            "price": "$3,650",
            "location": "Large selection of cars at wholesale prices motorhubnj.com"
        },
        {
            "title": "State inspection for ny cars",
            "url": "https://newyork.craigslist.org/que/wto/d/state-inspection-for-ny-cars/7815222455.html",
            "price": "$140",
            "location": "Queens jfk Brooklyn Nassau valley stream"
        },
        {
            "title": "Children's Books About Cars, Boats and Trains",
            "url": "https://newyork.craigslist.org/lgi/bks/d/bellmore-childrens-books-about-cars/7810837790.html",
            "price": "$1",
            "location": "Bellmore"
        },
        {
            "title": "Junk Cars Wanted",
            "url": "https://newyork.craigslist.org/lgi/wan/d/new-hyde-park-junk-cars-wanted/7815199601.html",
            "price": "0",
            "location": "New Hyde Park"
        },
        {
            "title": "The Cars of Oldsmobile and other books",
            "url": "https://newyork.craigslist.org/lgi/bks/d/east-northport-the-cars-of-oldsmobile/7812247157.html",
            "price": "$5",
            "location": "E. Northport"
        },
        {
            "title": "Temporary Plate",
            "url": "https://newyork.craigslist.org/brk/pts/d/brooklyn-temporary-plate/7809578370.html",
            "price": "$135",
            "location": "brooklyn"
        },
        {
            "title": "6 TOY CARS",
            "url": "https://newyork.craigslist.org/wch/tag/d/hawthorne-toy-cars/7812612289.html",
            "price": "$15",
            "location": "westchester"
        },
        {
            "title": "$$ TOP DOLLAR CASH FOR ALL CARS TRUCKS VANS SUVs AND MORE $$$",
            "url": "https://newyork.craigslist.org/que/wad/d/ozone-park-top-dollar-cash-for-all-cars/7815086995.html",
            "price": "0",
            "location": "queens"
        },
        {
            "title": "01\u2019 Chevy Tahoe plow truck &other old cars BEST OFFER over",
            "url": "https://newyork.craigslist.org/fct/pts/d/new-fairfield-01-chevy-tahoe-plow-truck/7809170968.html",
            "price": "$400",
            "location": "New fairfield CT"
        },
        {
            "title": "WANTED: SMART CARS & PARTS",
            "url": "https://newyork.craigslist.org/fct/wan/d/new-fairfield-wanted-smart-cars-parts/7809484321.html",
            "price": "0",
            "location": "Fairfield county"
        },
        {
            "title": "Disney cars",
            "url": "https://newyork.craigslist.org/brx/tag/d/new-york-disney-cars/7814968821.html",
            "price": "$10",
            "location": "New York"
        },
        {
            "title": "Junk Cars And Truck Pick up Today",
            "url": "https://newyork.craigslist.org/stn/cto/d/staten-island-junk-cars-and-truck-pick/7814948258.html",
            "price": "$2,500",
            "location": "Staten Island"
        },
        {
            "title": "TLC CARS FOR RENT 929x271x7711",
            "url": "https://newyork.craigslist.org/brk/pts/d/brooklyn-tlc-cars-for-rent-929x271x7711/7809219074.html",
            "price": "$400",
            "location": "Brooklyn"
        },
        {
            "title": "TLC CARS FOR RENT 929x271x7711",
            "url": "https://newyork.craigslist.org/brk/pts/d/brooklyn-tlc-cars-for-rent-929x271x7711/7809218139.html",
            "price": "$400",
            "location": "Brooklyn"
        },
        {
            "title": "Mobile dent repair auto body work on the spot",
            "url": "https://newyork.craigslist.org/que/cto/d/ozone-park-mobile-dent-repair-auto-body/7814938844.html",
            "price": "$199",
            "location": "we come to you"
        },
        {
            "title": "auto bodywork on the spot",
            "url": "https://newyork.craigslist.org/wch/cto/d/west-chester-auto-bodywork-on-the-spot/7814936125.html",
            "price": "$150",
            "location": "we come to you"
        },
        {
            "title": "Jabra SP700 for Cars",
            "url": "https://newyork.craigslist.org/que/pts/d/flushing-jabra-sp700-for-cars/7809510417.html",
            "price": "$20",
            "location": "Flushing"
        },
        {
            "title": "mr. fix it, mobile auto body on the spot",
            "url": "https://newyork.craigslist.org/que/cto/d/valley-stream-mr-fix-it-mobile-auto/7814733146.html",
            "price": "$175",
            "location": "queens"
        },
        {
            "title": "WE BUY SLOT CARS",
            "url": "https://newyork.craigslist.org/brk/wan/d/brooklyn-we-buy-slot-cars/7809012959.html",
            "price": "0",
            "location": "Brooklyn"
        },
        {
            "title": "slot cars wanted (Tjets)",
            "url": "https://newyork.craigslist.org/brk/wan/d/brooklyn-slot-cars-wanted-tjets/7809647250.html",
            "price": "0",
            "location": "Marine Park"
        },
        {
            "title": "WE BUY SLOT CARS",
            "url": "https://newyork.craigslist.org/brk/wan/d/brooklyn-we-buy-slot-cars/7809012753.html",
            "price": "0",
            "location": "Brooklyn"
        },
        {
            "title": "Matchbox/ Hot Wheels Cars/ Majorette or Small Trucks 1980's",
            "url": "https://newyork.craigslist.org/lgi/tag/d/matchbox-hot-wheels-cars-majorette-or/7807512957.html",
            "price": "$3",
            "location": "wantagh"
        },
        {
            "title": "Original '70s Vintage Slot Cars Aurora AFX, Tyco, LifeLike, T-Jet",
            "url": "https://newyork.craigslist.org/brk/ele/d/brooklyn-original-70s-vintage-slot-cars/7807033375.html",
            "price": "$399",
            "location": "Brooklyn NY"
        },
        {
            "title": "TLC CARS  FOR RENTED",
            "url": "https://newyork.craigslist.org/mnh/wtd/d/sunnyside-tlc-cars-for-rented/7814206541.html",
            "price": "$450",
            "location": "Midtown"
        },
        {
            "title": "Two reproduction murray sad face pedal cars",
            "url": "https://newyork.craigslist.org/lgi/clt/d/new-hyde-park-two-reproduction-murray/7806536619.html",
            "price": "$85",
            "location": "New hyde park"
        },
        {
            "title": "Hemi Muscle Cars by Robert Genat",
            "url": "https://newyork.craigslist.org/fct/pts/d/shelton-hemi-muscle-cars-by-robert-genat/7814173412.html",
            "price": "$15",
            "location": "Shelton"
        },
        {
            "title": "GM J-Cars 1982 - 1992 Haynes Repair Manual Sunbird Skyhawk Firenza Cim",
            "url": "https://newyork.craigslist.org/fct/pts/d/shelton-gm-cars-haynes-repair-manual/7814171298.html",
            "price": "$10",
            "location": "Shelton"
        },
        {
            "title": "Disney Cars and Planes w Color Changers",
            "url": "https://newyork.craigslist.org/stn/tag/d/staten-island-disney-cars-and-planes/7807343731.html",
            "price": "$1",
            "location": "staten island"
        },
        {
            "title": "Collectable trains&cars",
            "url": "https://newyork.craigslist.org/wch/clt/d/yonkers-collectable-trainscars/7814074917.html",
            "price": "$400",
            "location": "Yonkers"
        },
        {
            "title": "fast fix auto body on the spot mobile",
            "url": "https://newyork.craigslist.org/que/cto/d/ozone-park-fast-fix-auto-body-on-the/7814032318.html",
            "price": "$85",
            "location": "we come to you same day service"
        },
        {
            "title": "mr. fix it, auto Bodywork on the spot",
            "url": "https://newyork.craigslist.org/brk/cto/d/brooklyn-mr-fix-it-auto-bodywork-on-the/7814030571.html",
            "price": "$150",
            "location": "We come to you same day service"
        },
        {
            "title": "Toy cars",
            "url": "https://newyork.craigslist.org/que/tag/d/brooklyn-toy-cars/7814011749.html",
            "price": "$12",
            "location": "ridgewood"
        },
        {
            "title": "BLACK ZONE CAR SERVICES/ ALL CARS NEED TO BE FIX/",
            "url": "https://newyork.craigslist.org/brx/wto/d/mount-vernon-black-zone-car-services/7813985498.html",
            "price": "$100",
            "location": "bronx"
        },
        {
            "title": "Instant Cash for All Types of Vehicles: Old, Used, Unwanted Cars, Truc",
            "url": "https://newyork.craigslist.org/brk/wan/d/brooklyn-instant-cash-for-all-types-of/7813912287.html",
            "price": "0",
            "location": "brooklyn"
        },
        {
            "title": "We Buy All Cars Cash",
            "url": "https://newyork.craigslist.org/brk/cto/d/brooklyn-we-buy-all-cars-cash/7813917592.html",
            "price": "$2,000",
            "location": "718-501-5497"
        },
        {
            "title": "Instant Cash for All Types of Vehicles: Old, Used, Unwanted Cars, Truc",
            "url": "https://newyork.craigslist.org/brk/cto/d/brooklyn-instant-cash-for-all-types-of/7813913131.html",
            "price": "$5,000",
            "location": "brooklyn"
        },
        {
            "title": "Disney Pixar Cars NASCAR Die-cast Car",
            "url": "https://newyork.craigslist.org/fct/tag/d/milford-disney-pixar-cars-nascar-die/7811097870.html",
            "price": "$35",
            "location": "Milford"
        },
        {
            "title": "Mr. fix it, auto bodywork on the spot",
            "url": "https://newyork.craigslist.org/brk/cto/d/brooklyn-mr-fix-it-auto-bodywork-on-the/7813528388.html",
            "price": "$150",
            "location": "We come to you same day service"
        },
        {
            "title": ">> WE BUY CARS - INSTANT QUOTE - USED & JUNK <<",
            "url": "https://newyork.craigslist.org/brx/wad/d/bronx-we-buy-cars-instant-quote-used/7813362225.html",
            "price": "0",
            "location": "NYC/NJ/CT"
        },
        {
            "title": "3 Greenlight 1988 Ford Mustang 5.0 LX Foxbody Diecast cars exclusive l",
            "url": "https://newyork.craigslist.org/brk/clt/d/brooklyn-greenlight-1988-ford-mustang/7813207128.html",
            "price": "$120",
            "location": "brooklyn"
        },
        {
            "title": "3 Greenlight 1991 Ford Mustang 5.0 GT Foxbody Diecast cars Two-Tone ex",
            "url": "https://newyork.craigslist.org/brk/clt/d/brooklyn-greenlight-1991-ford-mustang/7813206791.html",
            "price": "$120",
            "location": "brooklyn"
        },
        {
            "title": "3 Greenlight 1991 Ford Mustang 5.0 GT Foxbody stripes Diecast cars exc",
            "url": "https://newyork.craigslist.org/brk/clt/d/brooklyn-greenlight-1991-ford-mustang/7813206332.html",
            "price": "$120",
            "location": "brooklyn"
        },
        {
            "title": "Uber Lyft TLC cars for rent",
            "url": "https://newyork.craigslist.org/que/cto/d/astoria-uber-lyft-tlc-cars-for-rent/7813126005.html",
            "price": "$395",
            "location": "Astoria"
        },
        {
            "title": "Uber Lyft TLC cars for rent",
            "url": "https://newyork.craigslist.org/que/cto/d/astoria-uber-lyft-tlc-cars-for-rent/7813123058.html",
            "price": "$395",
            "location": "Astoria"
        },
        {
            "title": "Uber Lyft TLC cars for rent",
            "url": "https://newyork.craigslist.org/que/cto/d/astoria-uber-lyft-tlc-cars-for-rent/7813122854.html",
            "price": "$395",
            "location": "Astoria"
        },
        {
            "title": "Vintage Model Train Set Fleischmann HO Engine and Cars In Boxes",
            "url": "https://newyork.craigslist.org/brk/clt/d/brooklyn-vintage-model-train-set/7812925999.html",
            "price": "$495",
            "location": "Brooklyn"
        },
        {
            "title": "Rear track bar for GM cars from 1982 to 1996",
            "url": "https://newyork.craigslist.org/brx/pts/d/bronx-rear-track-bar-for-gm-cars-from/7805747950.html",
            "price": "$200",
            "location": "bronx"
        },
        {
            "title": "ScharkSpark Brushless RC Cars for Adults, Max 70 KPH LAST ONE",
            "url": "https://newyork.craigslist.org/que/tag/d/ozone-park-scharkspark-brushless-rc/7812805035.html",
            "price": "$85",
            "location": "ozone park"
        },
        {
            "title": "4 16 inch pilot wheels 5x114 fits many cars",
            "url": "https://newyork.craigslist.org/wch/wto/d/peekskill-16-inch-pilot-wheels-5x114/7810911728.html",
            "price": "$500",
            "location": "peekskill"
        },
        {
            "title": "Sell Me Your Toyota Supra 1986 to 1992 Shell / Parts Cars / Wrecked",
            "url": "https://newyork.craigslist.org/que/pts/d/south-ozone-park-sell-me-your-toyota/7812674148.html",
            "price": "$0",
            "location": "queens"
        },
        {
            "title": "Vintage Matchbox Cars & Aurora Postage Stamp Train Set",
            "url": "https://newyork.craigslist.org/mnh/clt/d/new-york-vintage-matchbox-cars-aurora/7812286253.html",
            "price": "$0",
            "location": "Inwood / Wash Hts"
        },
        {
            "title": "WE BUY CARS TODAY",
            "url": "https://newyork.craigslist.org/stn/cto/d/staten-island-we-buy-cars-today/7812266005.html",
            "price": "$6,000",
            "location": "Staten Island"
        },
        {
            "title": "2013 Dodge Durango Sxt Awd 7 seater 100 plus cheap cars in stock",
            "url": "https://newyork.craigslist.org/brx/ctd/d/burlington-2013-dodge-durango-sxt-awd/7812259742.html",
            "price": "$5,995",
            "location": "Large selection of cars at wholesale prices motorhubnj.com"
        },
        {
            "title": "Cars",
            "url": "https://newyork.craigslist.org/que/cto/d/ozone-park-cars/7812193999.html",
            "price": "$4,000",
            "location": "S Ozone Park"
        },
        {
            "title": "2004 Gmc Envoy SLT 4x4 100 plus cheap cars and suvs in stock",
            "url": "https://newyork.craigslist.org/brk/ctd/d/burlington-2004-gmc-envoy-slt-4x4-100/7812147015.html",
            "price": "$2,395",
            "location": "Large selection of cars at wholesale prices motorhubnj.com"
        },
        {
            "title": "Collectable Toy Trucks & Cars",
            "url": "https://newyork.craigslist.org/lgi/clt/d/valley-stream-collectable-toy-trucks/7804222333.html",
            "price": "$5",
            "location": "Valley Stream"
        },
        {
            "title": "SUV Cars For Sale (914)-490-5912",
            "url": "https://newyork.craigslist.org/wch/ctd/d/yonkers-suv-cars-for-sale/7812020498.html",
            "price": "$1,995",
            "location": "Yonkers"
        },
        {
            "title": "MTH Southern Pacific Passengers cars",
            "url": "https://newyork.craigslist.org/que/art/d/woodhaven-mth-southern-pacific/7812017056.html",
            "price": "$25",
            "location": "Woodhaven, NY"
        },
        {
            "title": "Sedans For Sale (914)-490-5912",
            "url": "https://newyork.craigslist.org/wch/ctd/d/yonkers-sedans-for-sale/7812016219.html",
            "price": "$1,995",
            "location": "Yonkers"
        },
        {
            "title": "MTH NEW HAVEN EP-5 and Cars",
            "url": "https://newyork.craigslist.org/fct/tag/d/white-plains-mth-new-haven-ep-and-cars/7811824615.html",
            "price": "$450",
            "location": "White Plains"
        },
        {
            "title": "RC Cars",
            "url": "https://newyork.craigslist.org/wch/tag/d/mount-vernon-rc-cars/7803772381.html",
            "price": "$40",
            "location": "Mount Vernon"
        },
        {
            "title": "VINTAGE TOY CARS MATCHBOX & HOT WHEELS ...",
            "url": "https://newyork.craigslist.org/brk/tag/d/brooklyn-vintage-toy-cars-matchbox-hot/7811592622.html",
            "price": "$10",
            "location": "Brooklyn"
        },
        {
            "title": "Model Cars Collection",
            "url": "https://newyork.craigslist.org/brk/clt/d/brooklyn-model-cars-collection/7811552742.html",
            "price": "$599",
            "location": "Brooklyn"
        },
        {
            "title": "We buy all cars",
            "url": "https://newyork.craigslist.org/brk/pts/d/brooklyn-we-buy-all-cars/7811386736.html",
            "price": "$2,000",
            "location": "Brooklyn"
        },
        {
            "title": "Selling off fleet of SMART  CARS",
            "url": "https://newyork.craigslist.org/fct/cto/d/new-fairfield-selling-off-fleet-of/7811345314.html",
            "price": "$2,500",
            "location": "NEW FAIRFIELD CONNECTICUT"
        },
        {
            "title": "Lot of 3 Athearn HO Scale Model Train Cars with Boxes",
            "url": "https://newyork.craigslist.org/fct/atq/d/bridgewater-lot-of-athearn-ho-scale/7810899525.html",
            "price": "$30",
            "location": "Bridgewater, CT"
        },
        {
            "title": "Probe,   and cars,trucks for parts or whole",
            "url": "https://newyork.craigslist.org/wch/pts/d/yonkers-probe-and-carstrucks-for-parts/7803069687.html",
            "price": "$0",
            "location": "Yonker"
        },
        {
            "title": "WE BUY CARS NY WE WILL BEAT ANY OFFER YOU GOT",
            "url": "https://newyork.craigslist.org/que/cto/d/howard-beach-we-buy-cars-ny-we-will/7810728507.html",
            "price": "$2,150",
            "location": "Howard Beach"
        },
        {
            "title": "HOT WHEELS STORAGE CASE w/ 76 CARS--42 \"HOT WHEELS\"--34 OTHER BRANDS",
            "url": "https://newyork.craigslist.org/que/tag/d/oakland-gardens-hot-wheels-storage-case/7810680502.html",
            "price": "$26",
            "location": "Bayside"
        },
        {
            "title": "WANTED: Crashed-Damaged- Cars....",
            "url": "https://newyork.craigslist.org/brx/pts/d/new-york-wanted-crashed-damaged-cars/7810596854.html",
            "price": "$500",
            "location": "All Boros  All NY"
        },
        {
            "title": "WANTED: Crashed-Damaged- Cars....",
            "url": "https://newyork.craigslist.org/brx/pts/d/new-york-wanted-crashed-damaged-cars/7810596790.html",
            "price": "$500",
            "location": "All Boros  All NY"
        },
        {
            "title": "Lionel Great Train Robbery,Extra Engine,Cars,Fort&Lehigh Valley & P-38",
            "url": "https://newyork.craigslist.org/brx/tag/d/bronx-lionel-great-train-robberyextra/7810563955.html",
            "price": "$695",
            "location": "bronx"
        },
        {
            "title": "Maisto 2015 mustang gt 5.0 Coyote set 1:18 scale diecast cars 25 each",
            "url": "https://newyork.craigslist.org/brk/clt/d/brooklyn-maisto-2015-mustang-gt-50/7810178522.html",
            "price": "$75",
            "location": "brooklyn"
        },
        {
            "title": "We Buy Cars Today",
            "url": "https://newyork.craigslist.org/stn/cto/d/staten-island-we-buy-cars-today/7810124387.html",
            "price": "$6,000",
            "location": "Staten Island"
        },
        {
            "title": "CAR EAGLE HOOD ORNAMENT FOR CARS, OR PISTON KEY CHAIN",
            "url": "https://newyork.craigslist.org/que/pts/d/oakland-gardens-car-eagle-hood-ornament/7801773131.html",
            "price": "$5",
            "location": "bayside/queens"
        },
        {
            "title": "Free toy cars",
            "url": "https://newyork.craigslist.org/mnh/bab/d/new-york-free-toy-cars/7809691922.html",
            "price": "$0",
            "location": "Upper East Side"
        },
        {
            "title": "Dash Cam FHD 1080P Car Camera, Front Dash Camera for Cars",
            "url": "https://newyork.craigslist.org/que/ele/d/ozone-park-dash-cam-fhd-1080p-car/7809531305.html",
            "price": "$65",
            "location": "ozone park"
        },
        {
            "title": "2009 Ford Crown Vic P71 Runs looks great 100 plus cheap cars in stock",
            "url": "https://newyork.craigslist.org/que/ctd/d/burlington-2009-ford-crown-vic-p71-runs/7809445488.html",
            "price": "$2,500",
            "location": "Large selection of cars at wholesale prices motorhubnj.com"
        },
        {
            "title": "2002 Honda Civic Lx Runs looks great. 100 plus cars and suvs in stock",
            "url": "https://newyork.craigslist.org/brk/ctd/d/burlington-2002-honda-civic-lx-runs/7809431204.html",
            "price": "$2,395",
            "location": "Large selection of cars at wholesale prices motorhubnj.com"
        },
        {
            "title": "Lot of Assorted Vintage Mini Metal Cars, Figures, etc.",
            "url": "https://newyork.craigslist.org/que/atq/d/howard-beach-lot-of-assorted-vintage/7801462541.html",
            "price": "$20",
            "location": "Howard Beach"
        },
        {
            "title": "LIONEL STANDARD O GAUGE NY CENTRAL 3 CAR BOXED FREIGHT CARS",
            "url": "https://newyork.craigslist.org/lgi/clt/d/cedarhurst-lionel-standard-gauge-ny/7801945272.html",
            "price": "$65",
            "location": "FIVE TOWNS"
        },
        {
            "title": "2011 Hess toy trucks and race cars (2 items)",
            "url": "https://newyork.craigslist.org/mnh/tag/d/new-york-2011-hess-toy-trucks-and-race/7809259739.html",
            "price": "$30",
            "location": "Chinatown / Lit Italy"
        },
        {
            "title": "buying all cars trucks vans paying top dollar call today cash on the spot",
            "url": "https://newyork.craigslist.org/brk/cto/d/brooklyn-buying-all-cars-trucks-vans/7809047749.html",
            "price": "$2,000",
            "location": "Brooklyn"
        },
        {
            "title": "We buy cars and trucks up $3000",
            "url": "https://newyork.craigslist.org/lgi/cto/d/new-hyde-park-we-buy-cars-and-trucks-up/7809047558.html",
            "price": "$3,000",
            "location": "long island"
        },
        {
            "title": "WE BUY CARS NY WE WILL BEAT ANY OFFER YOU GOT",
            "url": "https://newyork.craigslist.org/que/cto/d/howard-beach-we-buy-cars-ny-we-will/7808986985.html",
            "price": "$2,150",
            "location": "Howard beach"
        },
        {
            "title": "AVIGO Plastic Double Sided Ramp Skateboard / Bike / Scooter / RC Cars",
            "url": "https://newyork.craigslist.org/stn/for/d/staten-island-avigo-plastic-double/7800828374.html",
            "price": "$25",
            "location": "Staten Island"
        },
        {
            "title": "Dash Cam FHD 1080P Car Camera, Front Dash Camera for Cars",
            "url": "https://newyork.craigslist.org/que/ele/d/ozone-park-dash-cam-fhd-1080p-car/7804940041.html",
            "price": "$65",
            "location": "ozone park"
        },
        {
            "title": "We buy all cars trucks SUVs vans",
            "url": "https://newyork.craigslist.org/que/wad/d/south-richmond-hill-we-buy-all-cars/7808708102.html",
            "price": "0",
            "location": "All ny queens Long Island ny bk bx si"
        },
        {
            "title": "Hess Truck - Race Cars",
            "url": "https://newyork.craigslist.org/wch/tag/d/yorktown-heights-hess-truck-race-cars/7808683603.html",
            "price": "$20",
            "location": "Yorktown Heights"
        },
        {
            "title": "2015 Ford Explorer Police Package awd 100 plus cheap cars in stock",
            "url": "https://newyork.craigslist.org/que/ctd/d/burlington-2015-ford-explorer-police/7808607216.html",
            "price": "$4,995",
            "location": "Large selection of cars at wholesale prices motorhubnj.com"
        },
        {
            "title": "We buy cars pay up to $2500",
            "url": "https://newyork.craigslist.org/que/cto/d/brooklyn-we-buy-cars-pay-up-to-2500/7808525949.html",
            "price": "$2,500",
            "location": "brooklyn"
        },
        {
            "title": "Hotwheels toys - Batman diecast Hot Wheels toy cars",
            "url": "https://newyork.craigslist.org/mnh/clt/d/new-york-hotwheels-toys-batman-diecast/7800828990.html",
            "price": "$12",
            "location": "Union Square"
        },
        {
            "title": "Hotwheels toys - 10 Tokyo Olympics diecast Hot Wheels toy cars",
            "url": "https://newyork.craigslist.org/mnh/clt/d/new-york-hotwheels-toys-10-tokyo/7800827744.html",
            "price": "$20",
            "location": "Union Square"
        },
        {
            "title": "Trade  VERY Nice laptop for Slot cars",
            "url": "https://newyork.craigslist.org/brk/wan/d/brooklyn-trade-very-nice-laptop-for/7800109937.html",
            "price": "0",
            "location": "Sheepshead bay"
        },
        {
            "title": "1967/68 Mercury Cougar parts",
            "url": "https://newyork.craigslist.org/brk/pts/d/staten-island-mercury-cougar-parts/7810829769.html",
            "price": "$1",
            "location": "Staten Island"
        },
        {
            "title": "4 tires 225/45/18 pirelli all season Runflat",
            "url": "https://newyork.craigslist.org/que/wto/d/flushing-tires-pirelli-all-season/7815970302.html",
            "price": "$320",
            "location": "Flushing Queens"
        },
        {
            "title": "Graco SnugFit 35 Infant Car Seat | Baby Car Seat with Anti Rebound Bar",
            "url": "https://newyork.craigslist.org/brk/bab/d/brooklyn-graco-snugfit-35-infant-car/7808636805.html",
            "price": "$75",
            "location": "Park Slope"
        },
        {
            "title": "1 tires 275/35/21 Michelin Pilot Sport all season",
            "url": "https://newyork.craigslist.org/que/wto/d/flushing-tires-michelin-pilot-sport-all/7815968892.html",
            "price": "$200",
            "location": "Flushing Queens"
        },
        {
            "title": "New Vintage Retro Thunder Cats - Lionel, Panther, Cheetara and He-man",
            "url": "https://newyork.craigslist.org/mnh/for/d/new-york-new-vintage-retro-thunder-cats/7815970366.html",
            "price": "$15",
            "location": "Upper East Side"
        },
        {
            "title": "FREE CREDIT CARD MACHINE-- FREE CASH REGISTER!!!",
            "url": "https://newyork.craigslist.org/mnh/bfd/d/new-york-free-credit-card-machine-free/7815968953.html",
            "price": "$0",
            "location": "Financial District"
        },
        {
            "title": "Hot Wheels Floating Bath Toys",
            "url": "https://newyork.craigslist.org/mnh/bab/d/hot-wheels-floating-bath-toys/7815967572.html",
            "price": "$15",
            "location": "TriBeCa"
        },
        {
            "title": "1970-72 (PARTS LOT) OLDSMOBILE CUTLASS/442/SX",
            "url": "https://newyork.craigslist.org/lgi/pts/d/merrick-parts-lot-oldsmobile-cutlass/7810062674.html",
            "price": "$90",
            "location": "North Merrick, Long Island,NY"
        },
        {
            "title": "Dash Cam",
            "url": "https://newyork.craigslist.org/brk/pts/d/brooklyn-dash-cam/7815960872.html",
            "price": "$65",
            "location": "Brooklyn"
        },
        {
            "title": "Collectible Tins - American Bandstand - M&M and More",
            "url": "https://newyork.craigslist.org/lgi/clt/d/valley-stream-collectible-tins-american/7811005768.html",
            "price": "$10",
            "location": "Valley Stream"
        },
        {
            "title": "Commercial Property for Sale - by owner",
            "url": "https://newyork.craigslist.org/brk/bfs/d/poughkeepsie-commercial-property-for/7815369771.html",
            "price": "$699,000",
            "location": "HIGHLAND"
        },
        {
            "title": "Commercial Property for Sale - by owner",
            "url": "https://newyork.craigslist.org/mnh/bfs/d/poughkeepsie-commercial-property-for/7815369626.html",
            "price": "$699,000",
            "location": "HIGHLAND"
        },
        {
            "title": "Volkswagen Passat 2015 miles 58,000",
            "url": "https://newyork.craigslist.org/lgi/cto/d/new-york-volkswagen-passat-2015-miles/7815952021.html",
            "price": "$7,900",
            "location": "New York"
        },
        {
            "title": "Ford fusion 2011",
            "url": "https://newyork.craigslist.org/brk/cto/d/brooklyn-ford-fusion-2011/7815951240.html",
            "price": "$3,900",
            "location": "brooklyn"
        },
        {
            "title": "2011 BMW X3 excellent condition",
            "url": "https://newyork.craigslist.org/stn/cto/d/staten-island-2011-bmw-x3-excellent/7815950847.html",
            "price": "$6,000",
            "location": "Valley stream"
        },
        {
            "title": "Yakima Frontloader Bike Rack",
            "url": "https://newyork.craigslist.org/mnh/spo/d/new-york-yakima-frontloader-bike-rack/7815935637.html",
            "price": "$75",
            "location": "New York"
        },
        {
            "title": "2013 Honda Civic Sdn 4dr Man Si ***Guaranteed Financing!!!",
            "url": "https://newyork.craigslist.org/lgi/ctd/d/lynbrook-2013-honda-civic-sdn-4dr-man/7815935594.html",
            "price": "$10,500",
            "location": "+ ACA Auto Sales"
        },
        {
            "title": "2010 Subaru Outback 4dr Wgn H4 Auto 2.5i Premium All-Weather ***Guaranteed Finan",
            "url": "https://newyork.craigslist.org/lgi/ctd/d/lynbrook-2010-subaru-outback-4dr-wgn-h4/7815935563.html",
            "price": "$5,995",
            "location": "+ ACA Auto Sales"
        },
        {
            "title": "2016 Chrysler Town  Country 4dr Wgn Touring ***Guaranteed Financing!!!",
            "url": "https://newyork.craigslist.org/lgi/ctd/d/lynbrook-2016-chrysler-town-country-4dr/7815935522.html",
            "price": "$6,995",
            "location": "+ ACA Auto Sales"
        },
        {
            "title": "2010 Toyota RAV4 4WD 4dr 4-cyl 4-Spd AT ***Guaranteed Financing!!!",
            "url": "https://newyork.craigslist.org/lgi/ctd/d/lynbrook-2010-toyota-rav4-4wd-4dr-cyl/7815935489.html",
            "price": "$6,800",
            "location": "+ ACA Auto Sales"
        },
        {
            "title": "2011 Jeep Grand Cherokee 4WD 4dr Laredo ***Guaranteed Financing!!!",
            "url": "https://newyork.craigslist.org/lgi/ctd/d/lynbrook-2011-jeep-grand-cherokee-4wd/7815935460.html",
            "price": "$5,995",
            "location": "+ ACA Auto Sales"
        },
        {
            "title": "2011 Honda CR-V 4WD 5dr EX ***Guaranteed Financing!!!",
            "url": "https://newyork.craigslist.org/lgi/ctd/d/lynbrook-2011-honda-cr-4wd-5dr-ex/7815935429.html",
            "price": "$8,300",
            "location": "+ ACA Auto Sales"
        },
        {
            "title": "2012 Acura TL 4dr Sdn Auto 2WD Tech ***Guaranteed Financing!!!",
            "url": "https://newyork.craigslist.org/lgi/ctd/d/lynbrook-2012-acura-tl-4dr-sdn-auto-2wd/7815935408.html",
            "price": "$7,600",
            "location": "+ ACA Auto Sales"
        },
        {
            "title": "2013 Hyundai Tucson FWD 4dr Auto GLS ***Guaranteed Financing!!!",
            "url": "https://newyork.craigslist.org/lgi/ctd/d/lynbrook-2013-hyundai-tucson-fwd-4dr/7815935378.html",
            "price": "$5,700",
            "location": "+ ACA Auto Sales"
        },
        {
            "title": "2018 Volkswagen Tiguan Limited 2.0T 4MOTION ***Guaranteed Financing!!!",
            "url": "https://newyork.craigslist.org/lgi/ctd/d/lynbrook-2018-volkswagen-tiguan-limited/7815935353.html",
            "price": "$8,400",
            "location": "+ ACA Auto Sales"
        },
        {
            "title": "2014 BMW X3 AWD 4dr xDrive28i ***Guaranteed Financing!!!",
            "url": "https://newyork.craigslist.org/lgi/ctd/d/lynbrook-2014-bmw-x3-awd-4dr-xdrive28i/7815935320.html",
            "price": "$8,400",
            "location": "+ ACA Auto Sales"
        },
        {
            "title": "2012 Ford E-350 E-350 Super Duty Van",
            "url": "https://newyork.craigslist.org/que/ctd/d/floral-park-2012-ford-350-350-super/7815934299.html",
            "price": "$12,450",
            "location": "Floral Park"
        },
        {
            "title": "2012 Ford E-350 E-350 Super Duty Van",
            "url": "https://newyork.craigslist.org/que/ctd/d/floral-park-2012-ford-350-350-super/7815934269.html",
            "price": "$9,850",
            "location": "Floral Park"
        },
        {
            "title": "2014 Ford E-350 E-350 Super Duty Van",
            "url": "https://newyork.craigslist.org/que/ctd/d/floral-park-2014-ford-350-350-super/7815934259.html",
            "price": "$9,850",
            "location": "Floral Park"
        },
        {
            "title": "Brass ACF Builders Plate From NY City Subway Car American Car & Foundr",
            "url": "https://newyork.craigslist.org/stn/clt/d/staten-island-brass-acf-builders-plate/7813797468.html",
            "price": "$100",
            "location": "Staten Island"
        },
        {
            "title": "(5) Vintage 1988 Hot Wheels Volkswagon",
            "url": "https://newyork.craigslist.org/fct/clt/d/brookfield-vintage-1988-hot-wheels/7811700959.html",
            "price": "$10",
            "location": "Brookfield, CT"
        },
        {
            "title": "Futura trailer for sale",
            "url": "https://newyork.craigslist.org/stn/tro/d/staten-island-futura-trailer-for-sale/7815928306.html",
            "price": "$15,500",
            "location": "Staten Island"
        },
        {
            "title": "2024 Nautique Super Air Nautique G23",
            "url": "https://newyork.craigslist.org/brk/ctd/d/staten-island-2024-nautique-super-air/7815922471.html",
            "price": "$179,999",
            "location": "+ Brooklyn Auto Sales"
        },
        {
            "title": "Snow tires on wheels 4",
            "url": "https://newyork.craigslist.org/fct/wto/d/norwalk-snow-tires-on-wheels/7812016731.html",
            "price": "$299",
            "location": "East Norwalk"
        },
        {
            "title": "8 Vintage Movie Posters -- Any one for $10",
            "url": "https://newyork.craigslist.org/brk/clt/d/brooklyn-vintage-movie-posters-any-one/7812710006.html",
            "price": "$10",
            "location": "Brooklyn"
        },
        {
            "title": "2021 Nissan Sentra SV $62 A WEEK!",
            "url": "https://newyork.craigslist.org/lgi/ctd/d/cambria-heights-2021-nissan-sentra-sv/7815914390.html",
            "price": "$0",
            "location": "+ EVERYONE DRIVES! WE MAKE IT HAPPEN!"
        },
        {
            "title": "2016 Ford Transit Wagon T-350 148 Low Roof XLT Swing-Out RH Dr ONE OWNER! $",
            "url": "https://newyork.craigslist.org/lgi/ctd/d/cambria-heights-2016-ford-transit-wagon/7815910716.html",
            "price": "$0",
            "location": "+ EVERYONE DRIVES! WE MAKE IT HAPPEN!"
        },
        {
            "title": "2011 Ford E-series E 150 XLT 3dr Passenger Van $32 A WEEK!",
            "url": "https://newyork.craigslist.org/lgi/ctd/d/cambria-heights-2011-ford-series-150/7815910157.html",
            "price": "$0",
            "location": "+ EVERYONE DRIVES! WE MAKE IT HAPPEN!"
        },
        {
            "title": "2015 Nissan Rogue SV. LOW MILES!!! $56 A WEEK!",
            "url": "https://newyork.craigslist.org/que/ctd/d/cambria-heights-2015-nissan-rogue-sv/7815908599.html",
            "price": "$0",
            "location": "+ EVERYONE DRIVES! WE MAKE IT HAPPEN!"
        },
        {
            "title": "2014 Jeep Grand Cherokee Limited. CLEAN CARFAX! $80 A WEEK!",
            "url": "https://newyork.craigslist.org/lgi/ctd/d/cambria-heights-2014-jeep-grand/7815908402.html",
            "price": "$0",
            "location": "+ EVERYONE DRIVES! WE MAKE IT HAPPEN!"
        },
        {
            "title": "2017 Bentley Bentayga W12 AWD",
            "url": "https://newyork.craigslist.org/brk/ctd/d/staten-island-2017-bentley-bentayga-w12/7815901744.html",
            "price": "$74,999",
            "location": "+ Brooklyn Auto Sales"
        },
        {
            "title": "On30 Scale Train Hawthorne Village Wild Song Combine Car",
            "url": "https://newyork.craigslist.org/mnh/clt/d/new-york-on30-scale-train-hawthorne/7812338156.html",
            "price": "$30",
            "location": "Financial District"
        },
        {
            "title": "2022 Ram 3500 Tradesman",
            "url": "https://newyork.craigslist.org/brk/ctd/d/commack-2022-ram-3500-tradesman/7815884128.html",
            "price": "$45,995",
            "location": "+ Lemans Cars"
        },
        {
            "title": "2017 Porsche 911 Turbo S Coupe",
            "url": "https://newyork.craigslist.org/brk/ctd/d/staten-island-2017-porsche-911-turbo/7815877088.html",
            "price": "$152,999",
            "location": "+ Brooklyn Auto Sales"
        },
        {
            "title": "1991-2002 Saturn S Series ABS Sensors and Brackets",
            "url": "https://newyork.craigslist.org/stn/pts/d/staten-island-saturn-series-abs-sensors/7815876319.html",
            "price": "$75",
            "location": "staten island"
        },
        {
            "title": "Mercedes W113 230 SL Owner's Manual Kit & Parts Catalog - Complete -",
            "url": "https://newyork.craigslist.org/brx/pts/d/new-york-mercedes-sl-owners-manual-kit/7813674689.html",
            "price": "$550",
            "location": "NY"
        },
        {
            "title": "Porsche 928 Boge Struts, Shocks and Strut Mounts",
            "url": "https://newyork.craigslist.org/brx/pts/d/new-york-porsche-928-boge-struts-shocks/7813674931.html",
            "price": "$0",
            "location": "NY"
        },
        {
            "title": "Porsche Late 944/951/924 and 968 Upper Rear Seat",
            "url": "https://newyork.craigslist.org/brx/pts/d/new-york-porsche-late-and-968-upper/7808784229.html",
            "price": "$250",
            "location": "NY"
        },
        {
            "title": "Porsche 911 Carrera 3.2 Heat Exchangers",
            "url": "https://newyork.craigslist.org/lgi/pts/d/new-york-porsche-911-carrera-32-heat/7813675035.html",
            "price": "$550",
            "location": "NY"
        },
        {
            "title": "A LOT OF TOYS - Educational, recreational toys, puzzles, games...",
            "url": "https://newyork.craigslist.org/mnh/tag/d/new-york-lot-of-toys-educational/7811779579.html",
            "price": "$1",
            "location": "Upper West Side"
        },
        {
            "title": "FALCON &RANCHERO.PARTS 60/65",
            "url": "https://newyork.craigslist.org/que/pts/d/ozone-park-falcon-rancheroparts-60-65/7811027640.html",
            "price": "$10",
            "location": "OZONE PARK"
        },
        {
            "title": "71 CHEVY NOVA  MOLDINGS",
            "url": "https://newyork.craigslist.org/que/pts/d/ozone-park-71-chevy-nova-moldings/7811026781.html",
            "price": "$25",
            "location": "OZONE PARK"
        },
        {
            "title": "2   13 INCH WIRE HUBCAPS",
            "url": "https://newyork.craigslist.org/que/pts/d/ozone-park-13-inch-wire-hubcaps/7811022352.html",
            "price": "$10",
            "location": "OZONE PARK"
        },
        {
            "title": "12 INCH CROME  HUBCAPS    (NEW)",
            "url": "https://newyork.craigslist.org/que/wto/d/ozone-park-12-inch-crome-hubcaps-new/7810160247.html",
            "price": "$50",
            "location": "OZONE PARK"
        },
        {
            "title": "Matchbox Hotwheels floating bath toys",
            "url": "https://newyork.craigslist.org/mnh/tag/d/new-york-matchbox-hotwheels-floating/7808347781.html",
            "price": "$15",
            "location": "TriBeCa"
        },
        {
            "title": "2022 Mercedes-Benz SL-Class SL63",
            "url": "https://newyork.craigslist.org/brk/ctd/d/staten-island-2022-mercedes-benz-sl/7815850868.html",
            "price": "$112,999",
            "location": "+ Brooklyn Auto Sales"
        },
        {
            "title": "2 tires 275/35/21  Bridgestone Alenza Runflat",
            "url": "https://newyork.craigslist.org/que/wto/d/flushing-tires-bridgestone-alenza/7815849308.html",
            "price": "$280",
            "location": "Flushing Queens"
        },
        {
            "title": "Radio's Walkie-Talkies UHF/VHF 8 in total and lots of ACCESSORIES",
            "url": "https://newyork.craigslist.org/brk/ele/d/brooklyn-radios-walkie-talkies-uhf-vhf/7810035635.html",
            "price": "$200",
            "location": "Williamsburg"
        },
        {
            "title": "Subaru Outback OEM Rubber Floor mats - Gen 4 - 2010-2014",
            "url": "https://newyork.craigslist.org/brk/pts/d/brooklyn-subaru-outback-oem-rubber/7810038215.html",
            "price": "$40",
            "location": "Williamsburg"
        },
        {
            "title": "Baby\u2019s First Books, Games & Toys",
            "url": "https://newyork.craigslist.org/mnh/bab/d/new-york-babys-first-books-games-toys/7808343855.html",
            "price": "$20",
            "location": "TriBeCa"
        },
        {
            "title": "Baby\u2019s First Toys, Games & Books",
            "url": "https://newyork.craigslist.org/mnh/tag/d/new-york-babys-first-toys-games-books/7808240906.html",
            "price": "$20",
            "location": "TriBeCa"
        },
        {
            "title": "Baby\u2019s first Toys, Games & Books",
            "url": "https://newyork.craigslist.org/mnh/tag/d/new-york-babys-first-toys-games-books/7808221435.html",
            "price": "$20",
            "location": "TriBeCa"
        },
        {
            "title": "2011 Honda Pilot 4WD 4dr EX-L SUV",
            "url": "https://newyork.craigslist.org/que/ctd/d/north-babylon-2011-honda-pilot-4wd-4dr/7815840732.html",
            "price": "$0",
            "location": "West Babylon"
        },
        {
            "title": "2019 Audi A6 A6 quattro Premium",
            "url": "https://newyork.craigslist.org/brk/ctd/d/commack-2019-audi-a6-a6-quattro-premium/7815840655.html",
            "price": "$23,995",
            "location": "+ Lemans Cars"
        },
        {
            "title": "2017 Mercedes-Benz C-Class C300 4MATIC Coupe Coupe",
            "url": "https://newyork.craigslist.org/que/ctd/d/jamaica-2017-mercedes-benz-class-c300/7815841054.html",
            "price": "$0",
            "location": "Richmond Hill"
        },
        {
            "title": "2017 Ford Transit 250 Van Low Roof w/Sliding Pass. 130-in. WB Van",
            "url": "https://newyork.craigslist.org/que/ctd/d/jamaica-2017-ford-transit-250-van-low/7815841036.html",
            "price": "$0",
            "location": "Richmond Hill"
        },
        {
            "title": "2020 Dodge Grand Caravan SXT Minivan",
            "url": "https://newyork.craigslist.org/que/ctd/d/jamaica-2020-dodge-grand-caravan-sxt/7815841013.html",
            "price": "$0",
            "location": "Richmond Hill"
        },
        {
            "title": "2019 Jeep Compass Limited 4WD SUV",
            "url": "https://newyork.craigslist.org/que/ctd/d/jamaica-2019-jeep-compass-limited-4wd/7815840988.html",
            "price": "$0",
            "location": "Richmond Hill"
        },
        {
            "title": "2014 Lexus IS 250 AWD Sedan",
            "url": "https://newyork.craigslist.org/que/ctd/d/jamaica-2014-lexus-is-250-awd-sedan/7815840962.html",
            "price": "$0",
            "location": "Richmond Hill"
        },
        {
            "title": "2015 Ford Transit Connect Wagon Titanium w/Rear Liftgate LWB Van",
            "url": "https://newyork.craigslist.org/que/ctd/d/jamaica-2015-ford-transit-connect-wagon/7815840941.html",
            "price": "$0",
            "location": "Richmond Hill"
        },
        {
            "title": "2017 Ford Transit Connect Wagon Titanium w/Rear Liftgate LWB Van",
            "url": "https://newyork.craigslist.org/que/ctd/d/jamaica-2017-ford-transit-connect-wagon/7815840921.html",
            "price": "$0",
            "location": "Richmond Hill"
        },
        {
            "title": "2014 INFINITI Q60 Coupe Sport 6MT Coupe",
            "url": "https://newyork.craigslist.org/que/ctd/d/jamaica-2014-infiniti-q60-coupe-sport/7815840888.html",
            "price": "$0",
            "location": "Richmond Hill"
        },
        {
            "title": "2008 Nissan Rogue S AWD Crossover 4dr",
            "url": "https://newyork.craigslist.org/jsy/ctd/d/spotswood-2008-nissan-rogue-awd/7815824738.html",
            "price": "$4,800",
            "location": "East Brunswick, NJ"
        },
        {
            "title": "2014 Nissan Pathfinder SL 4x4 4dr SUV",
            "url": "https://newyork.craigslist.org/jsy/ctd/d/spotswood-2014-nissan-pathfinder-sl-4x4/7815824675.html",
            "price": "$6,800",
            "location": "East Brunswick, NJ"
        },
        {
            "title": "2002 Mercedes-Benz C Class C 32 AMG 4dr Sedan",
            "url": "https://newyork.craigslist.org/jsy/ctd/d/spotswood-2002-mercedes-benz-class-32/7815824585.html",
            "price": "$6,500",
            "location": "East Brunswick, NJ"
        },
        {
            "title": "2020 Porsche Panamera 4S",
            "url": "https://newyork.craigslist.org/brk/ctd/d/staten-island-2020-porsche-panamera-4s/7815823224.html",
            "price": "$69,999",
            "location": "+ Brooklyn Auto Sales"
        },
        {
            "title": "2016 Ford Flex Limited AWD  3.5 TURBO ECOBOOST **48K MILES**",
            "url": "https://newyork.craigslist.org/mnh/ctd/d/bensenville-2016-ford-flex-limited-awd/7815804916.html",
            "price": "$17,995",
            "location": "1081 Entry Drive  Bensenville, IL 60106"
        },
        {
            "title": "MATCHBOX HOT WHEELS PREMIUM CAR CULTURE SUPER MARIO BROS 64 KART BUNDLE LOT NIB ",
            "url": "https://newyork.craigslist.org/brk/tag/d/brooklyn-matchbox-hot-wheels-premium/7809032394.html",
            "price": "$375",
            "location": "BAY RIDGE"
        },
        {
            "title": "Mint Sizzlers Race Car Mega Charger Vehicle Recharger - New In Package",
            "url": "https://newyork.craigslist.org/brk/tag/d/brooklyn-mint-sizzlers-race-car-mega/7814512631.html",
            "price": "$30",
            "location": "Brooklyn NY"
        },
        {
            "title": "2011 Jeep Wrangler",
            "url": "https://newyork.craigslist.org/mnh/ctd/d/new-york-2011-jeep-wrangler/7815801932.html",
            "price": "$11,929",
            "location": "Autotrader Private Seller"
        },
        {
            "title": "2 tires 275/45. And 315/40/21 pirelli Scorpion zero",
            "url": "https://newyork.craigslist.org/que/wto/d/flushing-tires-and-pirelli-scorpion-zero/7815788640.html",
            "price": "$380",
            "location": "queens"
        },
        {
            "title": "2019 Acura RDX Base",
            "url": "https://newyork.craigslist.org/brk/ctd/d/commack-2019-acura-rdx-base/7815800750.html",
            "price": "$23,995",
            "location": "+ Lemans Cars"
        },
        {
            "title": "NOVA 71 LEFT ARM REST BASE&PAD",
            "url": "https://newyork.craigslist.org/que/pts/d/ozone-park-nova-71-left-arm-rest-basepad/7814949874.html",
            "price": "$10",
            "location": "OZONE PARK"
        },
        {
            "title": "Roadshock Defroster with Light",
            "url": "https://newyork.craigslist.org/que/ele/d/forest-hills-roadshock-defroster-with/7815788592.html",
            "price": "$10",
            "location": "Forest Hills"
        },
        {
            "title": "2014 Mercedes-Benz C Class C 300 Sport 4MATIC AWD 4dr Sedan",
            "url": "https://newyork.craigslist.org/jsy/ctd/d/spotswood-2014-mercedes-benz-class-300/7815779953.html",
            "price": "$7,800",
            "location": "East Brunswick, NJ"
        },
        {
            "title": "2015 Subaru Legacy 2.5i Limited AWD 4dr Sedan",
            "url": "https://newyork.craigslist.org/jsy/ctd/d/spotswood-2015-subaru-legacy-25i/7815779796.html",
            "price": "$6,500",
            "location": "East Brunswick, NJ"
        },
        {
            "title": "Set of 3 Usborne Books",
            "url": "https://newyork.craigslist.org/que/bab/d/jackson-heights-set-of-usborne-books/7811445067.html",
            "price": "$10",
            "location": "queens"
        },
        {
            "title": "CHEVY CAPRICE WAGON ECTO4",
            "url": "https://newyork.craigslist.org/mnh/cto/d/new-york-chevy-caprice-wagon-ecto4/7815775923.html",
            "price": "$23,000",
            "location": "Lower East Side"
        },
        {
            "title": "Down sizing sale",
            "url": "https://newyork.craigslist.org/stn/gms/d/staten-island-down-sizing-sale/7815765194.html",
            "price": "$0",
            "location": "staten island, New York"
        },
        {
            "title": "1994 320 SL",
            "url": "https://newyork.craigslist.org/stn/bar/d/staten-island-sl/7814668619.html",
            "price": "$0",
            "location": "Staten Island New York"
        },
        {
            "title": "2017 Smart ForTwo Electric Drive",
            "url": "https://newyork.craigslist.org/brk/cto/d/brooklyn-2017-smart-fortwo-electric/7815744431.html",
            "price": "$12,500",
            "location": "Williamsburg"
        },
        {
            "title": "Lionel Trains-Post War \"0\" Ga.",
            "url": "https://newyork.craigslist.org/brk/clt/d/franklin-lakes-lionel-trains-post-war-ga/7808632639.html",
            "price": "$7,500",
            "location": "Franklin Lakes"
        },
        {
            "title": "\u2588 JDM Made in Japan Xenon light HID Kit",
            "url": "https://newyork.craigslist.org/que/for/d/queens-village-jdm-made-in-japan-xenon/7812992491.html",
            "price": "$0",
            "location": "18 months warranty - Queens"
        },
        {
            "title": "Baby Jogger City Go Infant Black Base Only",
            "url": "https://newyork.craigslist.org/stn/bab/d/staten-island-baby-jogger-city-go/7809205979.html",
            "price": "$10",
            "location": "Staten Island"
        },
        {
            "title": "2017 Toyota 4Runner 4 Runner 4-Runner SR5 Premium - ONE OWNER ~ Craigs",
            "url": "https://newyork.craigslist.org/que/ctd/d/flushing-2017-toyota-4runner-runner/7815699388.html",
            "price": "$35,990",
            "location": "196-33 Northern Blvd, Queens NY, 11358"
        },
        {
            "title": "2012 Ford E-250 E-250 Van",
            "url": "https://newyork.craigslist.org/que/ctd/d/floral-park-2012-ford-250-250-van/7815699014.html",
            "price": "$11,850",
            "location": "Floral Park"
        },
        {
            "title": "2012 Ford E-350 E-350 Super Duty Extended Van",
            "url": "https://newyork.craigslist.org/que/ctd/d/floral-park-2012-ford-350-350-super/7815698993.html",
            "price": "$11,650",
            "location": "Floral Park"
        },
        {
            "title": "2014 Ford E-150 E-150 Van",
            "url": "https://newyork.craigslist.org/que/ctd/d/floral-park-2014-ford-150-150-van/7815698971.html",
            "price": "$8,950",
            "location": "Floral Park"
        },
        {
            "title": "2007 TOYOTA FJ CRUISER AWD",
            "url": "https://newyork.craigslist.org/brk/ctd/d/brooklyn-2007-toyota-fj-cruiser-awd/7815687112.html",
            "price": "$11,000",
            "location": "Brooklyn"
        },
        {
            "title": "2021 JEEP WRANGLER RUBICON AWD",
            "url": "https://newyork.craigslist.org/brk/ctd/d/brooklyn-2021-jeep-wrangler-rubicon-awd/7815686511.html",
            "price": "$29,995",
            "location": "Brooklyn"
        },
        {
            "title": "2022 BMW M5 CS",
            "url": "https://newyork.craigslist.org/brk/ctd/d/staten-island-2022-bmw-m5-cs/7815685095.html",
            "price": "$0",
            "location": "+ Brooklyn Auto Sales"
        },
        {
            "title": "Road champ minis lot",
            "url": "https://newyork.craigslist.org/lgi/tag/d/port-washington-road-champ-minis-lot/7809141019.html",
            "price": "$10",
            "location": "Port Washington"
        },
        {
            "title": "Hot wheels set",
            "url": "https://newyork.craigslist.org/brk/tag/d/brooklyn-hot-wheels-set/7810579926.html",
            "price": "$30",
            "location": "Brooklyn"
        },
        {
            "title": "2004 Porsche 911 Carrera Coupe",
            "url": "https://newyork.craigslist.org/brk/ctd/d/staten-island-2004-porsche-911-carrera/7815660854.html",
            "price": "$33,999",
            "location": "+ Brooklyn Auto Sales"
        },
        {
            "title": "1985-1993 MUSTANG'S WANTED",
            "url": "https://newyork.craigslist.org/lgi/pts/d/westbury-mustangs-wanted/7810566363.html",
            "price": "$1",
            "location": "Long Island NY"
        },
        {
            "title": "1985-1993 MUSTANG'S WANTED",
            "url": "https://newyork.craigslist.org/lgi/wan/d/westbury-mustangs-wanted/7810566391.html",
            "price": "0",
            "location": "Long Island NY"
        },
        {
            "title": "1997 Honda Orthia 2.0 GX RHD JDM IMPORT",
            "url": "https://newyork.craigslist.org/mnh/ctd/d/new-york-1997-honda-orthia-20-gx-rhd/7815651990.html",
            "price": "$13,900",
            "location": "manhattan"
        },
        {
            "title": "2019 Chevrolet Chevy Suburban LT",
            "url": "https://newyork.craigslist.org/brk/ctd/d/commack-2019-chevrolet-chevy-suburban-lt/7815642356.html",
            "price": "$26,995",
            "location": "+ Lemans Cars"
        },
        {
            "title": "2005 Lexus ES330 original owner 175K miles",
            "url": "https://newyork.craigslist.org/fct/cto/d/norwalk-2005-lexus-es330-original-owner/7815635574.html",
            "price": "$5,500",
            "location": "Norwalk CT"
        },
        {
            "title": "Large bag of mixed LEGOS",
            "url": "https://newyork.craigslist.org/mnh/tag/d/new-york-large-bag-of-mixed-legos/7811818387.html",
            "price": "$80",
            "location": "Inwood / Wash Hts"
        },
        {
            "title": "2015 BMW 6 series Alpina B6 xDrive GC ~ Craigslist Great Deal!",
            "url": "https://newyork.craigslist.org/que/ctd/d/flushing-2015-bmw-series-alpina-b6/7815633078.html",
            "price": "$35,752",
            "location": "196-33 Northern Blvd, Queens NY, 11358"
        },
        {
            "title": "2022 KTM 1290 Super Duke R",
            "url": "https://newyork.craigslist.org/brk/ctd/d/staten-island-2022-ktm-1290-super-duke/7815632492.html",
            "price": "$14,999",
            "location": "+ Brooklyn Auto Sales"
        },
        {
            "title": "2015 Volvo XC60 T6 Sport Utility 4D (2015.5)",
            "url": "https://newyork.craigslist.org/fct/cto/d/stamford-2015-volvo-xc60-t6-sport/7815626958.html",
            "price": "$13,900",
            "location": "Stamford"
        },
        {
            "title": "CADILLAC DEVILLE WINDOW REGULATOR",
            "url": "https://newyork.craigslist.org/que/pts/d/astoria-cadillac-deville-window/7815614351.html",
            "price": "$25",
            "location": "Queens"
        },
        {
            "title": "2013 Honda Civic",
            "url": "https://newyork.craigslist.org/lgi/cto/d/west-hempstead-2013-honda-civic/7815606833.html",
            "price": "$7,399",
            "location": "West Hempstead"
        },
        {
            "title": "2021 Tesla Model 3 Performance",
            "url": "https://newyork.craigslist.org/brk/ctd/d/staten-island-2021-tesla-model/7815602208.html",
            "price": "$0",
            "location": "+ Brooklyn Auto Sales"
        },
        {
            "title": "ECS Tuning Carbon Fiber steering wheel mini cooper r55 R56",
            "url": "https://newyork.craigslist.org/mnh/pts/d/new-york-ecs-tuning-carbon-fiber/7815599252.html",
            "price": "$250",
            "location": "New York"
        },
        {
            "title": "2013 Nissan Frontier SV V6 4x4 4dr King Cab 6.1 ft. SB Pickup 5A Call/Text 718-5",
            "url": "https://newyork.craigslist.org/brk/ctd/d/ridgewood-2013-nissan-frontier-sv-v6/7815597493.html",
            "price": "$0",
            "location": "+ ANY CREDIT APPROVED! GOOD CREDIT, BAD CREDIT, NO CREDIT!"
        },
        {
            "title": "Temporary Plates Insurance",
            "url": "https://newyork.craigslist.org/brk/pts/d/brooklyn-temporary-plates-insurance/7808494822.html",
            "price": "$155",
            "location": "brooklyn"
        },
        {
            "title": "2018 Jaguar F-PACE 25t Premium",
            "url": "https://newyork.craigslist.org/brk/ctd/d/commack-2018-jaguar-pace-25t-premium/7815591758.html",
            "price": "$16,995",
            "location": "+ Lemans Cars"
        },
        {
            "title": "2014 Honda Accord LX Sedan 6-Spd MT Sedan",
            "url": "https://newyork.craigslist.org/que/ctd/d/jamaica-2014-honda-accord-lx-sedan-spd/7815591559.html",
            "price": "$0",
            "location": "Richmond Hill"
        },
        {
            "title": "2022 Toyota Highlander XLE FWD V6 SUV",
            "url": "https://newyork.craigslist.org/que/ctd/d/jamaica-2022-toyota-highlander-xle-fwd/7815591525.html",
            "price": "$0",
            "location": "Richmond Hill"
        },
        {
            "title": "2015 Ford Transit Connect XL LWB Van",
            "url": "https://newyork.craigslist.org/que/ctd/d/jamaica-2015-ford-transit-connect-xl/7815591477.html",
            "price": "$0",
            "location": "Richmond Hill"
        },
        {
            "title": "2017 McLaren 570GT Base Coupe",
            "url": "https://newyork.craigslist.org/que/ctd/d/jamaica-2017-mclaren-570gt-base-coupe/7815591447.html",
            "price": "$0",
            "location": "Richmond Hill"
        },
        {
            "title": "2022 Cadillac Escalade Premium Luxury AWD SUV",
            "url": "https://newyork.craigslist.org/que/ctd/d/jamaica-2022-cadillac-escalade-premium/7815591418.html",
            "price": "$0",
            "location": "Richmond Hill"
        },
        {
            "title": "2019 Mercedes-Benz AMG GT Cabrio Convertible",
            "url": "https://newyork.craigslist.org/que/ctd/d/jamaica-2019-mercedes-benz-amg-gt/7815591392.html",
            "price": "$0",
            "location": "Richmond Hill"
        },
        {
            "title": "2019 Lexus GS Base Sedan",
            "url": "https://newyork.craigslist.org/que/ctd/d/jamaica-2019-lexus-gs-base-sedan/7815591360.html",
            "price": "$0",
            "location": "Richmond Hill"
        },
        {
            "title": "2018 Ford Transit 150 Wagon Med. Roof XL w/Sliding Pass. 130-in. WB Va",
            "url": "https://newyork.craigslist.org/que/ctd/d/jamaica-2018-ford-transit-150-wagon-med/7815591325.html",
            "price": "$0",
            "location": "Richmond Hill"
        },
        {
            "title": "2023 Toyota Sienna XLE 7-Passenger Minivan",
            "url": "https://newyork.craigslist.org/que/ctd/d/elmhurst-2023-toyota-sienna-xle/7815591290.html",
            "price": "$0",
            "location": "Elmhurst"
        },
        {
            "title": "2021 Mercedes-Benz C-Class AMG C 63 S Coupe",
            "url": "https://newyork.craigslist.org/que/ctd/d/elmhurst-2021-mercedes-benz-class-amg/7815591257.html",
            "price": "$0",
            "location": "Elmhurst"
        },
        {
            "title": "2019 Honda Civic LX ~ Craigslist Great Deal!",
            "url": "https://newyork.craigslist.org/que/ctd/d/flushing-2019-honda-civic-lx-great-deal/7815590630.html",
            "price": "$17,936",
            "location": "196-33 Northern Blvd, Queens NY, 11358"
        },
        {
            "title": "Selling That Classic Car?  Serious Buyer of Antique vehicles",
            "url": "https://newyork.craigslist.org/wch/wan/d/yorktown-heights-selling-that-classic/7808695249.html",
            "price": "0",
            "location": "New York"
        },
        {
            "title": "Oil Extractor Pump",
            "url": "https://newyork.craigslist.org/fct/pts/d/stamford-oil-extractor-pump/7814581034.html",
            "price": "$40",
            "location": "Stamford"
        },
        {
            "title": "2012 Nissan Versa 1.8 S 4dr Hatchback 4A",
            "url": "https://newyork.craigslist.org/jsy/ctd/d/spotswood-2012-nissan-versa-18-4dr/7815571000.html",
            "price": "$3,900",
            "location": "East Brunswick, NJ"
        },
        {
            "title": "2015 Volkswagen Golf TSI S 4dr Hatchback 6A",
            "url": "https://newyork.craigslist.org/jsy/ctd/d/spotswood-2015-volkswagen-golf-tsi-4dr/7815570890.html",
            "price": "$8,900",
            "location": "East Brunswick, NJ"
        },
        {
            "title": "2004 Ford Super Duty F-250 Lariat 4dr Crew Cab 4WD SB",
            "url": "https://newyork.craigslist.org/jsy/ctd/d/spotswood-2004-ford-super-duty-250/7815570767.html",
            "price": "$7,800",
            "location": "East Brunswick, NJ"
        },
        {
            "title": "2021 INFINITI Q50 RED SPORT 400 AWD",
            "url": "https://newyork.craigslist.org/brk/ctd/d/eastchester-2021-infiniti-q50-red-sport/7815569932.html",
            "price": "$31,885",
            "location": "+ EastChester Certified Motors"
        },
        {
            "title": "2021 Lamborghini Huracan EVO Coupe",
            "url": "https://newyork.craigslist.org/brk/ctd/d/staten-island-2021-lamborghini-huracan/7815569731.html",
            "price": "$244,999",
            "location": "+ Brooklyn Auto Sales"
        },
        {
            "title": "1968 Chevelle 14x5 GM Steel Rims Tires Pair",
            "url": "https://newyork.craigslist.org/lgi/wto/d/brightwaters-1968-chevelle-14x5-gm/7808009299.html",
            "price": "$100",
            "location": "bay shore"
        },
        {
            "title": "Wanted Old Motorcycles \ud83d\udcde(800)220-9683 www.wantedoldmotorcycles.com",
            "url": "https://newyork.craigslist.org/que/wad/d/fresh-meadows-wanted-old-motorcycles/7815559821.html",
            "price": "0",
            "location": "Call\ud83d\udcde1(800)220-9683  Website: www.wantedoldmotorcycles.com"
        },
        {
            "title": "7 New In Box 2006 Mattel Hot Wheels Redline Sizzlers Motorized Race",
            "url": "https://newyork.craigslist.org/brk/tag/d/brooklyn-new-in-box-2006-mattel-hot/7814365266.html",
            "price": "$99",
            "location": "Brooklyn NY"
        },
        {
            "title": "Vintage Aurora AFX HO Scale Slot Car Lot",
            "url": "https://newyork.craigslist.org/brk/tag/d/brooklyn-vintage-aurora-afx-ho-scale/7811222844.html",
            "price": "$399",
            "location": "Brooklyn NY"
        },
        {
            "title": "Vintage Carrera Servo 160 Slot Car Racing Set - German Made",
            "url": "https://newyork.craigslist.org/brk/tag/d/brooklyn-vintage-carrera-servo-160-slot/7812886022.html",
            "price": "$99",
            "location": "Brooklyn NY"
        },
        {
            "title": "48 Vintage 1969 Hot Wheels Redline Sizzler Car Fat Daddy ChopCycle Lot",
            "url": "https://newyork.craigslist.org/brk/tag/d/brooklyn-48-vintage-1969-hot-wheels/7811553300.html",
            "price": "$299",
            "location": "Brooklyn NY"
        },
        {
            "title": "Yakima Roof Rack System (Chevy Bolt 2023)",
            "url": "https://newyork.craigslist.org/brk/pts/d/brooklyn-yakima-roof-rack-system-chevy/7815550745.html",
            "price": "$325",
            "location": "Brooklyn"
        },
        {
            "title": "2019 Porsche Cayenne AWD W BOSE SOUND ~ Craigslist Great Deal!",
            "url": "https://newyork.craigslist.org/que/ctd/d/flushing-2019-porsche-cayenne-awd-bose/7815550949.html",
            "price": "$33,650",
            "location": "196-33 Northern Blvd, Queens NY, 11358"
        },
        {
            "title": "2021 Hyundai Tucson SE 13k miles",
            "url": "https://newyork.craigslist.org/que/cto/d/ridgewood-2021-hyundai-tucson-se-13k/7815550747.html",
            "price": "$17,770",
            "location": "Murray Hil"
        },
        {
            "title": "NameTrains D & F Wooden Letters on Wheels!",
            "url": "https://newyork.craigslist.org/mnh/bab/d/nametrains-wooden-letters-on-wheels/7808690654.html",
            "price": "$5",
            "location": "Chelsea"
        },
        {
            "title": "2023 Mercedes-Benz S-Class S 500 4MATIC Sedan",
            "url": "https://newyork.craigslist.org/wch/ctd/d/eastchester-2023-mercedes-benz-class/7815542496.html",
            "price": "$63,250",
            "location": "+ EastChester Certified Motors"
        },
        {
            "title": "2013 Ford F-150 F150 F 150 FX4",
            "url": "https://newyork.craigslist.org/brk/ctd/d/commack-2013-ford-150-f150-150-fx4/7815542398.html",
            "price": "$17,995",
            "location": "+ Lemans Cars"
        },
        {
            "title": "2022 Hyundai Elantra",
            "url": "https://newyork.craigslist.org/wch/ctd/d/freeport-2022-hyundai-elantra/7815542376.html",
            "price": "$16,926",
            "location": "+ South Shore Mitsubishi"
        },
        {
            "title": "2024 Ford Transit XLT Van",
            "url": "https://newyork.craigslist.org/que/ctd/d/sunnyside-2024-ford-transit-xlt-van/7815537073.html",
            "price": "$57,800",
            "location": "Long Island City"
        },
        {
            "title": "2023 Chevrolet Suburban Premier SUV",
            "url": "https://newyork.craigslist.org/que/ctd/d/sunnyside-2023-chevrolet-suburban/7815537092.html",
            "price": "$59,888",
            "location": "Long Island City"
        },
        {
            "title": "2023 Chevrolet Suburban Premier SUV",
            "url": "https://newyork.craigslist.org/que/ctd/d/sunnyside-2023-chevrolet-suburban/7815537045.html",
            "price": "$48,888",
            "location": "Long Island City"
        },
        {
            "title": "2022 Mercedes-Benz GLE-Class GLE 350 SUV",
            "url": "https://newyork.craigslist.org/que/ctd/d/sunnyside-2022-mercedes-benz-gle-class/7815537011.html",
            "price": "$46,995",
            "location": "Long Island City"
        },
        {
            "title": "2024 Acura MDX 3.5L SUV",
            "url": "https://newyork.craigslist.org/que/ctd/d/sunnyside-2024-acura-mdx-35l-suv/7815536985.html",
            "price": "$44,995",
            "location": "Long Island City"
        },
        {
            "title": "2022 Audi Q7 55 Premium SUV",
            "url": "https://newyork.craigslist.org/que/ctd/d/sunnyside-2022-audi-q7-55-premium-suv/7815536963.html",
            "price": "$40,888",
            "location": "Long Island City"
        },
        {
            "title": "2024 Honda Pilot EX-L SUV",
            "url": "https://newyork.craigslist.org/que/ctd/d/sunnyside-2024-honda-pilot-ex-suv/7815536934.html",
            "price": "$37,995",
            "location": "Long Island City"
        },
        {
            "title": "2024 BMW X3 sDrive30i SUV",
            "url": "https://newyork.craigslist.org/que/ctd/d/sunnyside-2024-bmw-x3-sdrive30i-suv/7815536900.html",
            "price": "$37,800",
            "location": "Long Island City"
        },
        {
            "title": "2023 Mitsubishi Outlander 40th Anniversary SUV",
            "url": "https://newyork.craigslist.org/que/ctd/d/sunnyside-2023-mitsubishi-outlander/7815536722.html",
            "price": "$32,800",
            "location": "Long Island City"
        },
        {
            "title": "2023 Chevrolet Blazer LT SUV",
            "url": "https://newyork.craigslist.org/que/ctd/d/sunnyside-2023-chevrolet-blazer-lt-suv/7815536665.html",
            "price": "$27,995",
            "location": "Long Island City"
        },
        {
            "title": "2021 Acura RDX Technology Package SUV",
            "url": "https://newyork.craigslist.org/que/ctd/d/sunnyside-2021-acura-rdx-technology/7815536698.html",
            "price": "$29,888",
            "location": "Long Island City"
        },
        {
            "title": "2023 Nissan Pathfinder S SUV",
            "url": "https://newyork.craigslist.org/que/ctd/d/sunnyside-2023-nissan-pathfinder-suv/7815536644.html",
            "price": "$27,888",
            "location": "Long Island City"
        },
        {
            "title": "2021 Honda Odyssey EX Minivan",
            "url": "https://newyork.craigslist.org/que/ctd/d/sunnyside-2021-honda-odyssey-ex-minivan/7815536619.html",
            "price": "$27,800",
            "location": "Long Island City"
        },
        {
            "title": "2023 Mazda CX-9 Touring SUV",
            "url": "https://newyork.craigslist.org/que/ctd/d/sunnyside-2023-mazda-cx-touring-suv/7815536585.html",
            "price": "$26,995",
            "location": "Long Island City"
        },
        {
            "title": "2020 Acura MDX 3.5L SUV",
            "url": "https://newyork.craigslist.org/que/ctd/d/sunnyside-2020-acura-mdx-35l-suv/7815536562.html",
            "price": "$25,800",
            "location": "Long Island City"
        },
        {
            "title": "2019 Mercedes-Benz Metris Cargo Van",
            "url": "https://newyork.craigslist.org/que/ctd/d/sunnyside-2019-mercedes-benz-metris/7815536539.html",
            "price": "$24,800",
            "location": "Long Island City"
        },
        {
            "title": "2015 Chevrolet Suburban LTZ SUV",
            "url": "https://newyork.craigslist.org/que/ctd/d/sunnyside-2015-chevrolet-suburban-ltz/7815536513.html",
            "price": "$14,888",
            "location": "Long Island City"
        }
    ]
}